odoomaker-0.0.0-py3.5-nspkg.pth
bobtemplates/odoo/__init__.py
bobtemplates/odoo/hooks.py
bobtemplates/odoo/addon/.mrbob.ini
bobtemplates/odoo/addon/+addon.name+/README.md.bob
bobtemplates/odoo/addon/+addon.name+/__init__.py
bobtemplates/odoo/addon/+addon.name+/__manifest__.py.bob
bobtemplates/odoo/addon/+addon.name+/static/description/icon.png
bobtemplates/odoo/model/.mrbob.ini
bobtemplates/odoo/model/demo/+model.name_underscored+.xml.bob
bobtemplates/odoo/model/models/+model.name_underscored+.py.bob
bobtemplates/odoo/model/security/+model.name_underscored+.xml.bob
bobtemplates/odoo/model/views/+model.name_underscored+.xml.bob
odoomaker-0.0.0.dist-info/DESCRIPTION.rst
odoomaker-0.0.0.dist-info/METADATA
odoomaker-0.0.0.dist-info/RECORD
odoomaker-0.0.0.dist-info/WHEEL
odoomaker-0.0.0.dist-info/metadata.json
odoomaker-0.0.0.dist-info/namespace_packages.txt
odoomaker-0.0.0.dist-info/top_level.txt
